MANIFEST.in
README.txt
setup.py
pySIMOD/__init__.py
pySIMOD/entropy.py
pySIMOD/pySIMOD.py
pySIMOD.egg-info/PKG-INFO
pySIMOD.egg-info/SOURCES.txt
pySIMOD.egg-info/dependency_links.txt
pySIMOD.egg-info/top_level.txt