Metadata-Version: 1.0
Name: pySIMOD
Version: 0.3
Summary: A collection of functions for spatial interaction modelling
Home-page: UNKNOWN
Author: Taylor Oshan
Author-email: tayoshan@gmail.com
License: MIT
Platform: UNKNOWN
